adafruit_logging.py
adafruit_circuitpython_logging-5.6.0.dist-info/licenses/LICENSE
adafruit_circuitpython_logging-5.6.0.dist-info/METADATA
adafruit_circuitpython_logging-5.6.0.dist-info/WHEEL
adafruit_circuitpython_logging-5.6.0.dist-info/top_level.txt
adafruit_circuitpython_logging-5.6.0.dist-info/RECORD
