Metadata-Version: 2.4
Name: adafruit-circuitpython-logging
Version: 5.6.0
Summary: Logging module for CircuitPython
Author-email: Adafruit Industries <circuitpython@adafruit.com>
License: MIT
Project-URL: Homepage, https://github.com/adafruit/Adafruit_CircuitPython_Logging
Keywords: adafruit,blinka,circuitpython,micropython,logging,logger
Classifier: Intended Audience :: Developers
Classifier: Topic :: Software Development :: Libraries
Classifier: Topic :: Software Development :: Embedded Systems
Classifier: Topic :: System :: Hardware
Classifier: License :: OSI Approved :: MIT License
Classifier: Programming Language :: Python :: 3
License-File: LICENSE
Requires-Dist: Adafruit-Blinka
Requires-Dist: typing-extensions
Provides-Extra: optional
Dynamic: license-file
